[
  {
    "userId": "1776936153936",
    "userName": "mayank",
    "items": [
      {
        "id": 1777958485090,
        "menuItem": {
          "id": 4,
          "name": "Chicken Burger",
          "category": "Snacks",
          "veg": false,
          "price": 150,
          "rating": [],
          "feedback": [],
          "prepTime": "18",
          "discount": 0,
          "description": {
            "en": "Crispy chicken fillet with lettuce, tomato, onion and mayo in a toasted sesame bun.",
            "hi": "टोस्टेड सीसम बन में सलाद, टमाटर, प्याज और मेयोनेज़ के साथ कुरकुरा चिकन फिलेट।",
            "kn": "ಟೋಸ್ಟೆಡ್ ಸೆಸಮ್ ಬನ್‌ನಲ್ಲಿ ಲೆಟ್ಯೂಸ್, ಟೊಮಾಟೋ, ಈರುಳ್ಳಿ ಮತ್ತು ಮೇಯೋನೆಸ್‌ನೊಂದಿಗೆ ಕುರುಕುರೆ ಚಿಕನ್ ಫಿಲ್ಲೆಟ್.",
            "te": "టోస్టెడ్ సెసమ్ బన్‌లో లెట్యూస్, టమాటో, గడ్డాలు మరియు మేయోనెజ్‌తో క్రిస్పీ చికెన్ ఫిల్లెట్."
          },
          "reviews": 0,
          "available": true,
          "image": "https://images.pexels.com/photos/1633578/pexels-photo-1633578.jpeg",
          "dishInfo": "Crispy chicken fillet with lettuce, tomato, onion and mayo in a toasted sesame bun."
        },
        "quantity": 1,
        "addedAt": "2026-05-05T05:21:25.090Z"
      }
    ],
    "totalItems": 1,
    "totalAmount": 150,
    "updatedAt": "2026-05-05T05:21:25.090Z"
  }
]